MANIFEST.in
README.rst
setup.py
milo/__init__.py
milo.egg-info/PKG-INFO
milo.egg-info/SOURCES.txt
milo.egg-info/dependency_links.txt
milo.egg-info/not-zip-safe
milo.egg-info/requires.txt
milo.egg-info/top_level.txt
milo/logger/__init__.py
milo/redis_utils/__init__.py
milo/web/__init__.py
milo/xml/__init__.py