Metadata-Version: 1.0
Name: milo
Version: 0.1.9
Summary: Useful Python code, primarily intented for the author's use.
Home-page: https://github.com/ShawnMilo/milo
Author: Shawn Milochik
Author-email: shawn@milochik.com
License: BSD
Keywords: milo stuff
Platform: UNKNOWN
